setup.py
shinkenplugins/__init__.py
shinkenplugins.plugins.drupal_status.egg-info/PKG-INFO
shinkenplugins.plugins.drupal_status.egg-info/SOURCES.txt
shinkenplugins.plugins.drupal_status.egg-info/dependency_links.txt
shinkenplugins.plugins.drupal_status.egg-info/entry_points.txt
shinkenplugins.plugins.drupal_status.egg-info/namespace_packages.txt
shinkenplugins.plugins.drupal_status.egg-info/requires.txt
shinkenplugins.plugins.drupal_status.egg-info/top_level.txt
shinkenplugins/plugins/__init__.py
shinkenplugins/plugins/drupal_status/__init__.py
shinkenplugins/plugins/drupal_status/drupal_status.py