Metadata-Version: 1.0
Name: shinkenplugins.plugins.drupal-status
Version: 1.0
Summary: A plugin to monitor Drupal status
Home-page: https://github.com/savoirfairelinux/sfl-shinken-plugins
Author: Frédéric Vachon
Author-email: frederic.vachon@savoirfairelinux.com
License: GPL3+
Platform: any
